.DS_Store
islander/__init__.py
islanders/__init__.py
islanders/dataset.py
islanders/dt.py
islanders/irdatacleaning/__init__.py
islanders/irdatacleaning/datacorrelation.py
islanders/irdatacleaning/datadiscovery.py
islanders/irdatacleaning/encoder2.py
islanders/irdatacleaning/featur_scaling.py
islanders/irdatacleaning/inconsistent_data.py
islanders/irdatacleaning/missingvalues.py
islanders/irdatacleaning/resource.py
islanders/irdatacleaning/stringtodatetime.py
islanders-2022.1.18.dist-info/LICENSE
islanders-2022.1.18.dist-info/METADATA
islanders-2022.1.18.dist-info/WHEEL
islanders-2022.1.18.dist-info/top_level.txt
islanders-2022.1.18.dist-info/RECORD
