Metadata-Version: 2.1
Name: islanders
Version: 2022.1.18
Summary: module designed to make your data preprocessing experience easier
Home-page: UNKNOWN
Author: Islander Intelligence (William McKeon)
Author-email: <IslanderRobotics@gmail.com>
License: UNKNOWN
Keywords: Python,Machine Learning,Artificial Intelligence,Data Science,Data Cleaning,isladner robotics
Platform: UNKNOWN
License-File: LICENSE
Requires-Dist: scikit-learn
Requires-Dist: pandas
Requires-Dist: matplotlib
Requires-Dist: irdatacleaning
